COPYING
ChangeLog
MANIFEST.in
README.rst
TODO
docutils_tinyhtml.py
md2html-tiny
rst2html-tiny
setup.py
tiny-writer.css
docutils_tinyhtmlwriter_fork.egg-info/PKG-INFO
docutils_tinyhtmlwriter_fork.egg-info/SOURCES.txt
docutils_tinyhtmlwriter_fork.egg-info/dependency_links.txt
docutils_tinyhtmlwriter_fork.egg-info/requires.txt
docutils_tinyhtmlwriter_fork.egg-info/top_level.txt