Metadata-Version: 1.1
Name: docutils-tinyhtmlwriter-fork
Version: 1.2.2
Summary: Docutils Writer producing Tiny HTML
Home-page: https://github.com/tomaskadlec/docutils-tinyhtmlwriter
Author: Tomas Kadlec
Author-email: tomas@tomaskadlec.net
License: BSD
Platform: UNKNOWN
Classifier: Development Status :: 5 - Production/Stable
Classifier: Environment :: Console
Classifier: Intended Audience :: Developers
Classifier: Intended Audience :: End Users/Desktop
Classifier: License :: OSI Approved :: BSD License
Classifier: Natural Language :: English
Classifier: Natural Language :: Czech
Classifier: Operating System :: OS Independent
Classifier: Programming Language :: Python :: 2
Classifier: Programming Language :: Python :: 3
Classifier: Topic :: Documentation
Classifier: Topic :: Software Development :: Documentation
Classifier: Topic :: Text Processing
Classifier: Topic :: Text Processing :: Markup
Classifier: Topic :: Utilities
Requires: docutils (>= 0.12)
